morecantile/__init__.py
morecantile/commons.py
morecantile/defaults.py
morecantile/errors.py
morecantile/models.py
morecantile/py.typed
morecantile/utils.py
morecantile/data/CDB1GlobalGrid.json
morecantile/data/CanadianNAD83_LCC.json
morecantile/data/EuropeanETRS89_LAEAQuad.json
morecantile/data/GNOSISGlobalGrid.json
morecantile/data/LINZAntarticaMapTilegrid.json
morecantile/data/NZTM2000Quad.json
morecantile/data/README.md
morecantile/data/UPSAntarcticWGS84Quad.json
morecantile/data/UPSArcticWGS84Quad.json
morecantile/data/UTM31WGS84Quad.json
morecantile/data/WGS1984Quad.json
morecantile/data/WebMercatorQuad.json
morecantile/data/WorldCRS84Quad.json
morecantile/data/WorldMercatorWGS84Quad.json
morecantile/scripts/__init__.py
morecantile/scripts/cli.py
morecantile-7.0.2.dist-info/METADATA
morecantile-7.0.2.dist-info/WHEEL
morecantile-7.0.2.dist-info/entry_points.txt
morecantile-7.0.2.dist-info/licenses/LICENSE
morecantile-7.0.2.dist-info/RECORD
