Metadata-Version: 2.4
Name: morecantile
Version: 7.0.2
Summary: Construct and use map tile grids (a.k.a TileMatrixSet / TMS).
Project-URL: Source, https://github.com/developmentseed/morecantile
Project-URL: Documentation, https://developmentseed.org/morecantile/
Author-email: Vincent Sarago <vincent@developmentseed.com>
License: MIT License
License-File: LICENSE
Keywords: GIS,Map Tile,TMS,TileMatrixSet
Classifier: Intended Audience :: Information Technology
Classifier: Intended Audience :: Science/Research
Classifier: License :: OSI Approved :: MIT License
Classifier: Programming Language :: Python :: 3.11
Classifier: Programming Language :: Python :: 3.12
Classifier: Programming Language :: Python :: 3.13
Classifier: Programming Language :: Python :: 3.14
Classifier: Topic :: Scientific/Engineering :: GIS
Requires-Python: >=3.11
Requires-Dist: attrs
Requires-Dist: click
Requires-Dist: pydantic~=2.0
Requires-Dist: pyproj<4.0,>=3.1
Provides-Extra: rasterio
Requires-Dist: rasterio>=1.2.1; extra == 'rasterio'
